{
  "id": "a41f5ad330b700a7",
  "url": "https://www.onmanorama.com/kerala/top-news/2026/05/26/vizhinjam-port-land-cargo-june.html",
  "title": "Land-based container movement from Vizhinjam likely to begin in June",
  "source": "Onmanorama",
  "publishedAt": "2026-05-26T11:09:49.000Z",
  "content": "Vizhinjam: Container movement from the Vizhinjam International Seaport through road networks is expected to begin in early June, with the road connecting the port to the Kazhakoottam–Karode bypass all set to open. Port authorities have submitted a letter to the State government informing that the road is ready for cargo operations and seeking further action. According to officials, the National Highways Authority of India must grant permission for traffic from the port through the bypass, and the government must take the necessary steps to secure it. Once approvals are in place and, depending on schedule availability, Chief Minister V D Satheesan is expected to inaugurate the new road as well as the commencement of land-based cargo movement in the first week of June. Meanwhile, customs clearance for cargo movement through land routes has already been obtained. In the initial phase, only the stretch towards the capital city will be opened to traffic. Trucks carrying containers bound for Tamil Nadu will travel along this route for a certain distance before entering the opposite carriageway as part of a temporary traffic arrangement. The 1.7-km stretch runs from the main entrance of the port through the Mulloor Kalungu junction to the bypass. Until the expanded road network in the cloverleaf model is complete, container movement to and from the port will be routed through this stretch."
}
